py_veo-1.5.0.data/data/share/py-veo/README.md
py_veo-1.5.0.data/data/share/py-veo/examples/Makefile
py_veo-1.5.0.data/data/share/py-veo/examples/average.py
py_veo-1.5.0.data/data/share/py-veo/examples/libvesleep.c
py_veo-1.5.0.data/data/share/py-veo/examples/libvetest2.c
py_veo-1.5.0.data/data/share/py-veo/examples/libvetest4.c
py_veo-1.5.0.data/data/share/py-veo/examples/libvetest5.c
py_veo-1.5.0.data/data/share/py-veo/examples/libvetest6.c
py_veo-1.5.0.data/data/share/py-veo/examples/libvetest7.c
py_veo-1.5.0.data/data/share/py-veo/examples/libvetest8.c
py_veo-1.5.0.data/data/share/py-veo/examples/libvetest9.f90
py_veo-1.5.0.data/data/share/py-veo/examples/test-veo.py
py_veo-1.5.0.data/data/share/py-veo/examples/test2-veo.py
py_veo-1.5.0.data/data/share/py-veo/examples/test3-veo.py
py_veo-1.5.0.data/data/share/py-veo/examples/test4-veo.py
py_veo-1.5.0.data/data/share/py-veo/examples/test5-veo.py
py_veo-1.5.0.data/data/share/py-veo/examples/test6-veo.py
py_veo-1.5.0.data/data/share/py-veo/examples/test7-veo.py
py_veo-1.5.0.data/data/share/py-veo/examples/test8-veo.py
py_veo-1.5.0.data/data/share/py-veo/examples/test9-veo.py
veo/__init__.py
veo/_veo.cpython-36m-x86_64-linux-gnu.so
veo/vebuild.py
veo/logging/__init__.py
veo/logging/_vp_logging.py
py_veo-1.5.0.dist-info/METADATA
py_veo-1.5.0.dist-info/WHEEL
py_veo-1.5.0.dist-info/top_level.txt
py_veo-1.5.0.dist-info/RECORD
py_veo.libs/libveo-6b12de09.so.1.0.0
