Metadata-Version: 2.1
Name: py-veo
Version: 1.5.0
Summary: Python bindings for the VE Offloading API
Home-page: https://github.com/sx-aurora/py-veo
Author: Erich Focht
Author-email: efocht@gmail.com
License: GPLv2
Platform: UNKNOWN
Classifier: Development Status :: 4 - Beta
Classifier: Environment :: Console
Classifier: Intended Audience :: Education
Classifier: Intended Audience :: Developers
Classifier: Intended Audience :: Science/Research
Classifier: License :: OSI Approved :: GNU General Public License (GPL)
Classifier: Operating System :: POSIX :: Linux
Classifier: Programming Language :: Python
Classifier: Topic :: Software Development :: Libraries :: Python Modules
Requires: future
Requires: numpy
Requires: psutil
